coloc_sat/__init__.py
coloc_sat/bytemaps.py
coloc_sat/config.yml
coloc_sat/config_hy2.yml
coloc_sat/era5_meta.py
coloc_sat/generate_coloc.py
coloc_sat/hy2_meta.py
coloc_sat/intersection.py
coloc_sat/intersection_tools.py
coloc_sat/parquet_coloc.py
coloc_sat/sar_meta.py
coloc_sat/smap_meta.py
coloc_sat/smos_meta.py
coloc_sat/tools.py
coloc_sat/version.py
coloc_sat/windsat_daily_v7.py
coloc_sat/windsat_meta.py
coloc_sat/scripts/__init__.py
coloc_sat/scripts/coloc_2_products.py
coloc_sat/scripts/coloc_between_product_and_mission.py
coloc_sat/scripts/coloc_from_parquet.py
coloc_sat-1.2.5.dist-info/AUTHORS.rst
coloc_sat-1.2.5.dist-info/LICENSE
coloc_sat-1.2.5.dist-info/METADATA
coloc_sat-1.2.5.dist-info/WHEEL
coloc_sat-1.2.5.dist-info/entry_points.txt
coloc_sat-1.2.5.dist-info/top_level.txt
coloc_sat-1.2.5.dist-info/RECORD
