Metadata-Version: 2.1
Name: coloc_sat
Version: 1.2.5
License: MIT
Requires-Python: >=3.9
License-File: LICENSE
License-File: AUTHORS.rst
Requires-Dist: geopandas
Requires-Dist: xarray-datatree
Requires-Dist: xsar>=2023.8
Requires-Dist: numpy
Requires-Dist: numba
Requires-Dist: xarray
Requires-Dist: h5netcdf
Requires-Dist: shapely
Requires-Dist: fsspec
Requires-Dist: affine
Requires-Dist: pandas
Requires-Dist: geopandas
Requires-Dist: dask
Requires-Dist: more-itertools
Requires-Dist: pyyaml
Requires-Dist: pyproj
Requires-Dist: xradarsat2
Requires-Dist: xarray-safe-s1
